relycomply_client/__init__.py
relycomply_client/cleartoml.py
relycomply_client/cli.py
relycomply_client/client.py
relycomply_client/credential_sources.py
relycomply_client/exceptions.py
relycomply_client/gql_generator.py
relycomply_client/helpers.py
relycomply_client/rc.py
relycomply_client/relycomply_gql_client.py
relycomply_client/risk_rating_runtime.py
relycomply_client/sync.py
relycomply_client/watch.py
relycomply_client-0.15.4.dist-info/METADATA
relycomply_client-0.15.4.dist-info/WHEEL
relycomply_client-0.15.4.dist-info/entry_points.txt
relycomply_client-0.15.4.dist-info/RECORD
