Metadata-Version: 2.4
Name: relycomply-client
Version: 0.15.4
Summary: A python client for the RelyComply platform
Project-URL: Repository, https://github.com/relycomply/relycomply/
Project-URL: Homepage, https://www.relycomply.com
Author-email: James Saunders <james@relycomply.com>
Requires-Python: <4.0,>=3.10
Requires-Dist: boto3
Requires-Dist: gql>=3.0.0
Requires-Dist: littleutils
Requires-Dist: pandas
Requires-Dist: pyarrow
Requires-Dist: pygments
Requires-Dist: pyyaml
Requires-Dist: requests
Requires-Dist: requests-toolbelt
Requires-Dist: tabulate
Requires-Dist: termcolor
Requires-Dist: toml
Requires-Dist: typer
Requires-Dist: watchfiles>=0.24.0
